LICENSE
MANIFEST.in
README.md
pavement.py
requirements-dev.txt
requirements.txt
setup.py
tox.ini
docs/Makefile
docs/make.bat
docs/source/README
docs/source/conf.py
docs/source/index.rst
docs/source/_static/.gitkeep
nagios_graphite/__init__.py
nagios_graphite/main.py
nagios_graphite/metadata.py
nagios_graphite.egg-info/PKG-INFO
nagios_graphite.egg-info/SOURCES.txt
nagios_graphite.egg-info/dependency_links.txt
nagios_graphite.egg-info/entry_points.txt
nagios_graphite.egg-info/not-zip-safe
nagios_graphite.egg-info/requires.txt
nagios_graphite.egg-info/top_level.txt
tests/test_main.py